led_driver_mocks/__init__.py
led_driver_mocks/driver_mocks/__init__.py
led_driver_mocks/driver_mocks/apa102_mock.py
led_driver_mocks/server/__init__.py
led_driver_mocks/server/led_simulator.py
led_driver_mocks/server/server.py
led_driver_mocks-0.0.1.dist-info/METADATA
led_driver_mocks-0.0.1.dist-info/WHEEL
led_driver_mocks-0.0.1.dist-info/top_level.txt
led_driver_mocks-0.0.1.dist-info/RECORD
